comcloud_txt_manager/__init__.py
comcloud_txt_manager-0.1.0.dist-info/METADATA
comcloud_txt_manager-0.1.0.dist-info/WHEEL
comcloud_txt_manager-0.1.0.dist-info/entry_points.txt
comcloud_txt_manager-0.1.0.dist-info/RECORD
