Metadata-Version: 2.4
Name: comcloud-txt-manager
Version: 0.1.0
Summary: Add your description here
Author-email: comcloud <2230817302@qq.com>
Requires-Python: >=3.10
Requires-Dist: chardet>=5.2.0
Requires-Dist: jieba>=0.42.1
Requires-Dist: mcp[cli]>=1.12.3
